setup.py
pagseguro/__init__.py
pagseguro/exceptions.py
pagseguro/local_settings.py
pagseguro/validators.py
pagseguro/api/__init__.py
pagseguro/api/base_payment.py
pagseguro/api/v2/__init__.py
pagseguro/api/v2/notification.py
pagseguro/api/v2/payment.py
pagseguro/api/v2/schemas.py
pagseguro/api/v2/settings.py
pagseguro/api/v2/settings_sandbox.py
pagseguro/api/v2/transaction.py
pagseguro/tests/__init__.py
pagseguro/tests/payment.py
pagseguro_python.egg-info/PKG-INFO
pagseguro_python.egg-info/SOURCES.txt
pagseguro_python.egg-info/dependency_links.txt
pagseguro_python.egg-info/pbr.json
pagseguro_python.egg-info/requires.txt
pagseguro_python.egg-info/top_level.txt