Metadata-Version: 1.1
Name: pagseguro-python
Version: 0.37
Summary: PagSeguro API v.2 client library 
Home-page: https://github.com/ricardosasilva/pagseguro-python
Author: Ricardo Silva
Author-email: rsas79@gmail.com
License: UNKNOWN
Platform: UNKNOWN
Classifier: Development Status :: 3 - Alpha
